obynverifications/__init__.py
obynverifications/api.py
obynverifications/config.py
obynverifications/models.py
obynverifications/tasks.py
obynverifications/utils.py
obynverifications/verify.py
obyn_obynverifications-0.2.0.dist-info/METADATA
obyn_obynverifications-0.2.0.dist-info/WHEEL
obyn_obynverifications-0.2.0.dist-info/top_level.txt
obyn_obynverifications-0.2.0.dist-info/RECORD
