Metadata-Version: 2.1
Name: obyn-obynverifications
Version: 0.2.0
Summary: An verification plugin for ObynBot
Author: GizmoShiba
Author-email: gizmoshiba@gmail.com
Requires-Dist: disnake
Requires-Dist: obynutils
Requires-Dist: quart
Requires-Dist: sqlalchemy
